mylib_079/__init__.py
mylib_079-0.1.dist-info/LICENSE.txt
mylib_079-0.1.dist-info/METADATA
mylib_079-0.1.dist-info/WHEEL
mylib_079-0.1.dist-info/top_level.txt
mylib_079-0.1.dist-info/RECORD
