Metadata-Version: 2.1
Name: mylib-079
Version: 0.1
Summary: for calculating adding
Author: Arunpal Vikramsingh Thakur
Author-email: arunpalsinghthakur2727@gmail.com
Classifier: Programming Language :: Python :: 3
Classifier: License :: OSI Approved :: MIT License
Classifier: Operating System :: OS Independent
License-File: LICENSE.txt
